{
    "@context": [
        "https://w3id.org/ro/crate/1.2/context",
        {
            "bia": "https://bioimage-archive.org/ro-crate/",
            "obo": "http://purl.obolibrary.org/obo/",
            "dwc": "http://rs.tdwg.org/dwc/terms/",
            "dwciri": "http://rs.tdwg.org/dwc/iri/",
            "bao": "http://www.bioassayontology.org/bao#",
            "xsd": "http://www.w3.org/2001/XMLSchema#",
            "datePublished": {
                "@id": "http://schema.org/datePublished",
                "@type": "xsd:date"
            },
            "vernacularName": {
                "@id": "dwc:vernacularName"
            },
            "scientificName": {
                "@id": "dwc:scientificName"
            },
            "hasCellLine": {
                "@id": "bao:BAO_0002004"
            },
            "measurementMethod": {
                "@id": "dwciri:measurementMethod"
            },
            "taxonomicRange": {
                "@id": "http://schema.org/taxonomicRange"
            },
            "seeAlso": {
                "@id": "rdf:seeAlso"
            },
            "BioSample": {
                "@id": "http://schema.org/BioSample"
            },
            "LabProtocol": {
                "@id": "http://schema.org/LabProtocol"
            },
            "labEquipment": {
                "@id": "http://schema.org/labEquipment"
            }
        }
    ],
    "@graph": [
        {
            "@id": "ssbd-repos-000294-ro-crate-metadata.json",
            "@type": "CreativeWork",
            "conformsTo": {
                "@id": "https://w3id.org/ro/crate/1.2"
            },
            "about": {
                "@id": "https://ssbd.riken.jp/repository/ssbd-repos-000294/"
            }
        },
        {
            "@id": "https://ssbd.riken.jp/repository/ssbd-repos-000294/",
            "@type": "Dataset",
            "identifier": "ssbd-repos-000294",
            "name": "Time-lapse FRAP assay images of DNAPTP6 dynamics in cells or not",
            "description": "ssbd-repos-000294",
            "datePublished": "2023-07-20",
            "license": "https://creativecommons.org/licenses/by/4.0/",
            "keywords": [
                "Animals",
                "Mice",
                "RNA/chemistry[major]",
                "G-Quadruplexes[major]",
                "Stress Granules",
                "RNA, Messenger/genetics",
                "Neurons/metabolism"
            ],
            "publisher": {
                "@id": "https://ssbd.riken.jp/repository"
            },
            "author": [
                {
                    "@id": "#auth-001"
                },
                {
                    "@id": "#auth-002"
                }
            ],
            "seeAlso": [
                {
                    "@id": "https://doi.org/10.1126/sciadv.ade2035"
                }
            ],
            "about": [
                {
                    "@id": "http://purl.obolibrary.org/obo/NCBITaxon_10090"
                },
                {
                    "@id": "#biosample-1"
                }
            ],
            "measurementMethod": [
                {
                    "@id": "#imaging-protocol-1"
                },
                {
                    "@id": "http://purl.obolibrary.org/obo/FBbi_00000366"
                },
                {
                    "@id": "#imaging-protocol-2"
                },
                {
                    "@id": "http://purl.obolibrary.org/obo/FBbi_00000249"
                }
            ],
            "thumbnailUrl": [
                "https://ssbd.riken.jp/omero/webclient/?show=project-1055"
            ],
            "size": [
                {
                    "@id": "#total-dataset-size"
                },
                {
                    "@id": "#file-count"
                }
            ]
        },
        {
            "@id": "https://ssbd.riken.jp/repository",
            "@type": "Organization",
            "name": "SSBD:repository"
        },
        {
            "@id": "#auth-001",
            "@type": "Person",
            "name": "Norifumi Shioda",
            "email": "shioda@kumamoto-u.ac.",
            "description": "Organization: Kumamoto University; Department: Institute of Molecular Embryology and Ge- netics (IMEG); Laboratory: Department of Genomic Neurology",
            "affiliation": [
                {
                    "@id": "https://ror.org/02cgss904"
                }
            ]
        },
        {
            "@id": "#auth-002",
            "@type": "Person",
            "name": "Sefan Asamitsu",
            "email": "sefan.asamitsu@riken.jp",
            "description": "Organization: RIKEN; Department: Center for Biosystems Dynamics Research (BDR)",
            "affiliation": [
                {
                    "@id": "https://ror.org/01sjwvz98"
                }
            ]
        },
        {
            "@id": "https://ror.org/02cgss904",
            "@type": "Organization",
            "name": "Kumamoto University"
        },
        {
            "@id": "https://ror.org/01sjwvz98",
            "@type": "Organization",
            "name": "RIKEN"
        },
        {
            "@id": "https://doi.org/10.1126/sciadv.ade2035",
            "@type": "ScholarlyArticle",
            "name": "RNA G-quadruplex organizes stress granule assembly through DNAPTP6 in neurons.",
            "datePublished": "2023"
        },
        {
            "@id": "#biosample-1",
            "@type": "BioSample",
            "name": "C57BL/6J",
            "description": "C57BL/6J",
            "taxonomicRange": [
                {
                    "@id": "http://purl.obolibrary.org/obo/NCBITaxon_10090"
                }
            ],
            "hasCellLine": "CCL-131"
        },
        {
            "@id": "http://purl.obolibrary.org/obo/NCBITaxon_10090",
            "@type": "Taxon",
            "scientificName": "Mus musculus",
            "vernacularName": "mouse"
        },
        {
            "@id": "#imaging-protocol-1",
            "@type": "LabProtocol",
            "name": "FRAP",
            "description": "FRAP",
            "measurementTechnique": [
                {
                    "@id": "http://purl.obolibrary.org/obo/FBbi_00000366"
                }
            ]
        },
        {
            "@id": "#imaging-protocol-2",
            "@type": "LabProtocol",
            "name": "time lapse microscopy",
            "description": "time lapse microscopy",
            "measurementTechnique": [
                {
                    "@id": "http://purl.obolibrary.org/obo/FBbi_00000249"
                }
            ]
        },
        {
            "@id": "http://purl.obolibrary.org/obo/FBbi_00000366",
            "@type": "DefinedTerm",
            "name": "FRAP"
        },
        {
            "@id": "http://purl.obolibrary.org/obo/FBbi_00000249",
            "@type": "DefinedTerm",
            "name": "time lapse microscopy"
        },
        {
            "@id": "#total-dataset-size",
            "@type": "QuantitativeValue",
            "value": 1233433600,
            "description": "1.2 GB",
            "unitCode": "http://purl.obolibrary.org/obo/UO_0000233",
            "unitText": "bytes"
        },
        {
            "@id": "#file-count",
            "@type": "QuantitativeValue",
            "value": 5,
            "unitCode": "http://purl.obolibrary.org/obo/UO_0000189",
            "unitText": "file count"
        }
    ]
}
